{
"type": "FeatureCollection",
"name": "Bendungan_rencana_banjar",
"crs": { "type": "name", "properties": { "name": "urn:ogc:def:crs:OGC:1.3:CRS84" } },
"features": [
{ "type": "Feature", "properties": { "objectid": 328, "uid": "57bd5f97-db40-4be1-9fee-c5fd068cb10d", "creator": null, "created": 1667869207000.0, "updater": null, "updated": 1667869207000.0, "nm_balai": "BALAI WILAYAH SUNGAI KALIMANTAN III", "koord_x": 115.390944, "koord_y": -3.092913889, "data_src": null, "last_sync": null, "sync_notes": null, "no": null, "nm_inf": "Riam Kiwa", "kab": "KAB. BANJAR", "provinsi": "KALIMANTAN SELATAN", "pengelola": "BALAI WILAYAH SUNGAI KALIMANTAN III", "vol_bdgan": null, "status": null, "tahun_dat": null, "nama_ws": "BARITO", "nama_das": "BARITO", "tng_bdg": null, "pjn_tbh_bd": null, "tipe_bdgan": null, "ka_tam_tot": null, "ka_tam_ef": null, "ka_tam_mat": null, "lua_gng": null, "irigasi": null, "dmi": null, "plta": null, "rds_bjr": null, "thn_mulai": null, "thn_seles": null, "anak_sung": null, "induk_sung": null, "l_tangkap": null, "ch_tahun": null, "ch_desain": null, "d_desain": null, "pjg_plmp": null, "tipe_pelim": null, "jml_pintu": null, "p_mercu": null, "ele_mercu": null, "jenis": null, "remark": null, "foto": null, "urut": 250, "id": "06.03.21072901874", "kode": "-", "kode_balai": "B_KAL3", "kode_wilay": "04.A2.09", "kode_daera": "04.A2.09.002", "kewenangan": "Pusat", "lintas_kew": "Lintas Provinsi", "status_inf": "Tahap Rencana", "tahun_pemb": 0, "tipe_infra": "Urugan Batu", "volume_inf": null, "kecamatan": "Paramasan", "kelurahan": "Paramasan Bawah", "kondisi_ba": "Tidak Beroperasi", "tagging_pr": [ "KSPN SUPER PRIORITAS" ], "type": "Urugan Batu", "keterangan": "Urugan Batu (Inti Tegak Tanah Liat)", "kondisi_in": null, "tinggi_m": null, "tinggi_das": 110, "tinggi_d_1": 104.0, "panjang_m": null, "panjang_pu": 490, "lebar_m": null, "lebar_punc": 8, "elevasi_pu": 151.0, "volume_m3": null, "volume_tam": 52.970001220703125, "volume_t_1": 69.699996948242188, "volume_t_2": 90.510002136230469, "luas_genan": 1.860000014305115, "luas_gen_1": 5.0100002288818359, "luas_gen_2": 6.5399999618530282, "irigasi_ha": 1800, "dmi_m3_det": 45.0, "penguranga": 255.0, "penguran_1": 0, "plta_mwh": 6, "konsultan_": "Yellow River Engineering Consulting co., Ltd.", "tanggal_de": 0.0, "tanggal_ko": 0.0, "kontraktor": null, "supervisi": null, "biaya": "0", "tanggal_ma": null, "tanggal__1": null, "tahun_renc": null, "sejarah_si": null, "tanggal_pe": null, "tanggal_im": null, "type_pelim": "Pelimpah Luncur (Chute Spillway)", "dengan_pin": "YA", "pelimpah_k": "Ogee (Pelimpah Ambang Samping Berpintu)", "elevasi_me": 145.5, "pelimpah_l": 8.5, "lebar_amba": null, "pelimpah_p": 77.5, "panjang_sa": 310, "saluran_pe": null, "type_penga": "Bangunan Pengambilan (Intake) Tegak", "pengelak_k": "Intake Menara", "elevasi_da": null, "elevasi_in": 128, "lebar_pint": 2, "tinggi_pin": 2.5, "luas_tangk": 268.20001220703125, "debit_q100": 1078.1999511700001, "debit_qpmf": 2848.5, "debit_qpmp": 569.70001220703125, "volume_t_3": 6983, "elevasi_de": 134, "type_kolam": "Kolam Loncat Air (Plunge Pool)", "peredam_ke": "Mode disipasi energi dengan lompatan hidrolik", "panjang_ko": 77.5, "lebar_kola": 55, "masalah_ti": null, "plang_nama": null, "prasasti_p": null, "foto_1": null, "video_1": null, "updated_at": 1667550009000.0, "sta_hibah": null }, "geometry": { "type": "Point", "coordinates": [ 115.390944000000104, -3.092913888999931 ] } }
]
}
